odoo/addons/l10n_it_fatturapa_in/README.rst
odoo/addons/l10n_it_fatturapa_in/__init__.py
odoo/addons/l10n_it_fatturapa_in/__manifest__.py
odoo/addons/l10n_it_fatturapa_in/fields.py
odoo/addons/l10n_it_fatturapa_in/i18n/it.po
odoo/addons/l10n_it_fatturapa_in/i18n/l10n_it_fatturapa_in.pot
odoo/addons/l10n_it_fatturapa_in/migrations/16.0.1.1.0/post-migrate.py
odoo/addons/l10n_it_fatturapa_in/models/__init__.py
odoo/addons/l10n_it_fatturapa_in/models/account.py
odoo/addons/l10n_it_fatturapa_in/models/attachment.py
odoo/addons/l10n_it_fatturapa_in/models/company.py
odoo/addons/l10n_it_fatturapa_in/models/partner.py
odoo/addons/l10n_it_fatturapa_in/readme/CONFIGURE.md
odoo/addons/l10n_it_fatturapa_in/readme/CONTRIBUTORS.md
odoo/addons/l10n_it_fatturapa_in/readme/DESCRIPTION.md
odoo/addons/l10n_it_fatturapa_in/readme/INSTALL.md
odoo/addons/l10n_it_fatturapa_in/readme/ROADMAP.md
odoo/addons/l10n_it_fatturapa_in/readme/USAGE.md
odoo/addons/l10n_it_fatturapa_in/security/ir.model.access.csv
odoo/addons/l10n_it_fatturapa_in/security/rules.xml
odoo/addons/l10n_it_fatturapa_in/static/description/icon.png
odoo/addons/l10n_it_fatturapa_in/static/description/index.html
odoo/addons/l10n_it_fatturapa_in/static/src/img/icon.png
odoo/addons/l10n_it_fatturapa_in/tests/__init__.py
odoo/addons/l10n_it_fatturapa_in/tests/fatturapa_common.py
odoo/addons/l10n_it_fatturapa_in/tests/test_fix_bad_uris.py
odoo/addons/l10n_it_fatturapa_in/tests/test_import_fatturapa_xml.py
odoo/addons/l10n_it_fatturapa_in/tests/data/IT01234567890_FPR03.base64.xml.p7m
odoo/addons/l10n_it_fatturapa_in/tests/data/IT01234567890_FPR03.xml
odoo/addons/l10n_it_fatturapa_in/tests/data/IT01234567890_FPR03.xml.p7m
odoo/addons/l10n_it_fatturapa_in/tests/data/IT01234567890_FPR04.base64.xml.p7m
odoo/addons/l10n_it_fatturapa_in/tests/data/IT01234567890_FPR04.xml
odoo/addons/l10n_it_fatturapa_in/tests/data/IT01234567890_FPR05.xml
odoo/addons/l10n_it_fatturapa_in/tests/data/IT01234567890_FPR06.xml
odoo_addon_l10n_it_fatturapa_in-16.0.1.5.5.dist-info/METADATA
odoo_addon_l10n_it_fatturapa_in-16.0.1.5.5.dist-info/WHEEL
odoo_addon_l10n_it_fatturapa_in-16.0.1.5.5.dist-info/top_level.txt
odoo_addon_l10n_it_fatturapa_in-16.0.1.5.5.dist-info/RECORD
