Metadata-Version: 2.1
Name: odoo-addon-l10n_it_fatturapa_in
Version: 16.0.1.5.5
Requires-Python: >=3.10
Requires-Dist: asn1crypto
Requires-Dist: elementpath
Requires-Dist: odoo-addon-l10n_it_fatturapa>=16.0dev,<16.1dev
Requires-Dist: odoo-addon-l10n_it_fiscal_document_type>=16.0dev,<16.1dev
Requires-Dist: odoo-addon-l10n_it_withholding_tax_reason>=16.0dev,<16.1dev
Requires-Dist: odoo>=16.0a,<16.1dev
Summary: Ricezione fatture elettroniche
Home-page: https://github.com/OCA/l10n-italyl10n_it_fatturapa_in
License: AGPL-3
Author: Agile Business Group, Innoviu, Odoo Community Association (OCA)
Author-email: support@odoo-community.org
Classifier: Programming Language :: Python
Classifier: Framework :: Odoo
Classifier: Framework :: Odoo :: 16.0
Classifier: License :: OSI Approved :: GNU Affero General Public License v3
Classifier: Development Status :: 4 - Beta
